commonpasswords/__init__.py
commonpasswords/commonwords.txt
commonpasswords-1.0.dist-info/METADATA
commonpasswords-1.0.dist-info/WHEEL
commonpasswords-1.0.dist-info/licenses/LICENSE
commonpasswords-1.0.dist-info/RECORD
